starling/__init__.py
starling/app.py
starling/blueprint_action.py
starling/blueprint_scrapper.py
starling/config.py
starling/exception.py
starling/helper.py
starling/types.py
tests/__init__.py
tests/conftest.py
tests/starling/__init__.py
tests/starling/test_app.py
tests/starling/test_custom_error.py
kcd_starling-0.4.1.dist-info/METADATA
kcd_starling-0.4.1.dist-info/WHEEL
kcd_starling-0.4.1.dist-info/top_level.txt
kcd_starling-0.4.1.dist-info/RECORD
