Metadata-Version: 2.1
Name: kcd-starling
Version: 0.4.1
Summary: Skeleton for Scrapper
Home-page: UNKNOWN
Author: Terry Cho
Author-email: terry@kcd.co.kr
License: UNKNOWN
Platform: UNKNOWN
